cicada/__init__.py
cicada/clean.py
cicada/cli.py
cicada/cli_mapper.py
cicada/command_logger.py
cicada/commands.py
cicada/cooccurrence.py
cicada/editor_specs.py
cicada/entry_utils.py
cicada/index_mode.py
cicada/indexer.py
cicada/interactive_setup.py
cicada/interactive_setup_helpers.py
cicada/keyword_expander.py
cicada/keyword_search.py
cicada/keyword_test.py
cicada/logging_utils.py
cicada/parallel_expander.py
cicada/rest_server.py
cicada/scoring.py
cicada/setup.py
cicada/stats.py
cicada/status.py
cicada/version_check.py
cicada/watch_manager.py
cicada/watcher.py
cicada/agents/__init__.py
cicada/agents/generator.py
cicada/agents/installer.py
cicada/agents/templates/__init__.py
cicada/agents/templates/agents/__init__.py
cicada/agents/templates/agents/cicada-code-explorer.md
cicada/dead_code/__init__.py
cicada/dead_code/analyzer.py
cicada/dead_code/finder.py
cicada/embeddings/__init__.py
cicada/embeddings/indexer.py
cicada/embeddings/ollama.py
cicada/embeddings/searcher.py
cicada/embeddings/text_builder.py
cicada/extractors/__init__.py
cicada/extractors/base_signature.py
cicada/extractors/elixir_signature.py
cicada/extractors/keyword.py
cicada/extractors/python_signature.py
cicada/extractors/rust_signature.py
cicada/format/__init__.py
cicada/format/ascii_art.py
cicada/format/colors.py
cicada/format/formatter.py
cicada/git/__init__.py
cicada/git/cochange_analyzer.py
cicada/git/formatter.py
cicada/git/helper.py
cicada/git/history_analyzer.py
cicada/github/__init__.py
cicada/github/finder.py
cicada/github/pr_indexer/__init__.py
cicada/github/pr_indexer/github_api_client.py
cicada/github/pr_indexer/indexer.py
cicada/github/pr_indexer/line_mapper.py
cicada/github/pr_indexer/pr_index_builder.py
cicada/languages/__init__.py
cicada/languages/base.py
cicada/languages/formatter_interface.py
cicada/languages/formatter_registry.py
cicada/languages/clang/__init__.py
cicada/languages/clang/indexer.py
cicada/languages/dart/__init__.py
cicada/languages/dart/indexer.py
cicada_mcp-0.6.1.dist-info/METADATA
cicada_mcp-0.6.1.dist-info/WHEEL
cicada_mcp-0.6.1.dist-info/entry_points.txt
cicada_mcp-0.6.1.dist-info/licenses/LICENSE
cicada_mcp-0.6.1.dist-info/RECORD
