Metadata-Version: 2.4
Name: cicada-mcp
Version: 0.6.1
Summary: An Elixir and Python code intelligence MCP server
Project-URL: Homepage, https://github.com/wende/cicada
Project-URL: Repository, https://github.com/wende/cicada
Project-URL: Issues, https://github.com/wende/cicada/issues
Project-URL: Changelog, https://github.com/wende/cicada/blob/main/CHANGELOG.md
Project-URL: Documentation, https://github.com/wende/cicada#readme
Author-email: wende <wende@hey.com>
Maintainer-email: wende <wende@hey.com>
License-Expression: MIT
License-File: LICENSE
Keywords: ai-assistant,code-intelligence,code-search,developer-tools,elixir,git-history,mcp,model-context-protocol,phoenix,python
Classifier: Development Status :: 4 - Beta
Classifier: Framework :: Pytest
Classifier: Intended Audience :: Developers
Classifier: Operating System :: OS Independent
Classifier: Programming Language :: Python :: 3
Classifier: Programming Language :: Python :: 3.10
Classifier: Programming Language :: Python :: 3.11
Classifier: Programming Language :: Python :: 3.12
Classifier: Topic :: Software Development :: Code Generators
Classifier: Topic :: Software Development :: Libraries :: Python Modules
Classifier: Topic :: Software Development :: Version Control :: Git
Classifier: Topic :: Text Processing :: Indexing
Requires-Python: >=3.10
Requires-Dist: cicada-vector
Requires-Dist: fastapi>=0.115.0
Requires-Dist: gitpython>=3.1.0
Requires-Dist: jq>=1.6.0
Requires-Dist: lemminflect>=0.2.3
Requires-Dist: mcp>=0.1.0
Requires-Dist: pathspec>=0.12.0
Requires-Dist: pyyaml>=6.0
Requires-Dist: simple-term-menu>=1.6.0
Requires-Dist: tiktoken>=0.5.0
Requires-Dist: tomli>=2.0.0; python_version < '3.11'
Requires-Dist: tree-sitter-elixir>=0.1.0
Requires-Dist: tree-sitter-language-pack>=0.13.0
Requires-Dist: tree-sitter>=0.20.0
Requires-Dist: uvicorn>=0.32.0
Requires-Dist: watchdog>=3.0.0
Provides-Extra: all
Requires-Dist: cicada-scip>=0.1.0; extra == 'all'
Requires-Dist: gensim>=4.4.0; extra == 'all'
Requires-Dist: keybert>=0.8.0; extra == 'all'
Provides-Extra: dev
Requires-Dist: cicada-scip>=0.1.0; extra == 'dev'
Requires-Dist: pytest>=8.0; extra == 'dev'
Provides-Extra: ml
Requires-Dist: gensim>=4.4.0; extra == 'ml'
Requires-Dist: keybert>=0.8.0; extra == 'ml'
Provides-Extra: scip
Requires-Dist: cicada-scip>=0.1.0; extra == 'scip'
